pulumi_policy/__init__.py
pulumi_policy/deserialize.py
pulumi_policy/policy.py
pulumi_policy/proxy.py
pulumi_policy/pulumi-plugin.json
pulumi_policy/py.typed
pulumi_policy/secret.py
pulumi_policy/version.py
pulumi_policy-1.20.0.dist-info/METADATA
pulumi_policy-1.20.0.dist-info/WHEEL
pulumi_policy-1.20.0.dist-info/top_level.txt
pulumi_policy-1.20.0.dist-info/RECORD
