Metadata-Version: 2.4
Name: pulumi_policy
Version: 1.20.0
Summary: Pulumi's Policy Python SDK
Home-page: https://github.com/pulumi/pulumi-policy
License: Apache 2.0
Requires-Dist: pulumi<4.0.0,>=3.204.0
Requires-Dist: protobuf~=5.29.5
Requires-Dist: grpcio~=1.71
Requires-Dist: setuptools>=61.0
Dynamic: description
Dynamic: description-content-type
Dynamic: home-page
Dynamic: license
Dynamic: requires-dist
Dynamic: summary
